flapi/__comms.py
flapi/__context.py
flapi/__decorate.py
flapi/__enable.py
flapi/__init__.py
flapi/__main__.py
flapi/__util.py
flapi/_consts.py
flapi/cli/__init__.py
flapi/cli/consts.py
flapi/cli/install.py
flapi/cli/repl.py
flapi/cli/uninstall.py
flapi/cli/util.py
flapi/errors.py
flapi/py.typed
flapi/server/capout.py
flapi/server/consts.py
flapi/server/device_flapi_receive.py
flapi/server/device_flapi_respond.py
flapi/server/flapi_response.py
flapi-1.0.1.dist-info/LICENSE.md
flapi-1.0.1.dist-info/METADATA
flapi-1.0.1.dist-info/WHEEL
flapi-1.0.1.dist-info/entry_points.txt
flapi-1.0.1.dist-info/RECORD
