Metadata-Version: 2.1
Name: flapi
Version: 1.0.1
Summary: Remotely control FL Studio using the MIDI Controller Scripting API
Home-page: https://github.com/MiguelGuthridge/Flapi
License: MIT
Keywords: fl,studio,fl studio,midi,script,midi controller scripting,remote,remote control
Author: Miguel Guthridge
Author-email: hello@miguelguthridge.com
Requires-Python: >=3.9,<4.0
Classifier: Development Status :: 4 - Beta
Classifier: Environment :: Other Environment
Classifier: Intended Audience :: Developers
Classifier: License :: OSI Approved :: MIT License
Classifier: Operating System :: MacOS :: MacOS X
Classifier: Operating System :: Microsoft :: Windows
Classifier: Programming Language :: Python :: 3
Classifier: Programming Language :: Python :: 3.9
Classifier: Programming Language :: Python :: 3.10
Classifier: Programming Language :: Python :: 3.11
Classifier: Programming Language :: Python :: 3.12
Classifier: Typing :: Typed
Provides-Extra: ipython
Requires-Dist: click (>=8.1.7,<9.0.0)
Requires-Dist: click-default-group (>=1.2.4,<2.0.0)
Requires-Dist: fl-studio-api-stubs (>=28.2.2)
Requires-Dist: ipython (>=8.18.1,<9.0.0) ; extra == "ipython"
Requires-Dist: mido[ports-rtmidi] (>=1.3.2,<2.0.0)
Requires-Dist: typing-extensions (>=4.9.0,<5.0.0)
Project-URL: Bug Tracker, https://github.com/MiguelGuthridge/Flapi/issues
Project-URL: Online Documentation, https://miguelguthridge.github.io/Flapi
Project-URL: Repository, https://github.com/MiguelGuthridge/Flapi
